pddl2hoa/__init__.py
pddl2hoa/game.py
pddl2hoa/generate_hoa.py
pddl2hoa-0.1.4.dist-info/licenses/LICENSE.md
pddl2hoa-0.1.4.dist-info/METADATA
pddl2hoa-0.1.4.dist-info/WHEEL
pddl2hoa-0.1.4.dist-info/entry_points.txt
pddl2hoa-0.1.4.dist-info/top_level.txt
pddl2hoa-0.1.4.dist-info/RECORD
