Metadata-Version: 2.4
Name: pddl2hoa
Version: 0.1.4
Summary: Convert PDDL planning problems to HOA (Hanoi Omega Automata) format
Author-email: Oz Gitelson <oz@ozgitelson.com>
License: MIT
Project-URL: Homepage, https://github.com/ozgitelson/pddl2hoa
Project-URL: Repository, https://github.com/ozgitelson/pddl2hoa
Project-URL: Issues, https://github.com/ozgitelson/pddl2hoa/issues
Keywords: pddl,planning,automata,hoa,formal-methods
Classifier: Development Status :: 3 - Alpha
Classifier: License :: OSI Approved :: MIT License
Classifier: Programming Language :: Python :: 3
Classifier: Programming Language :: Python :: 3.8
Classifier: Programming Language :: Python :: 3.9
Classifier: Programming Language :: Python :: 3.10
Classifier: Topic :: Scientific/Engineering :: Artificial Intelligence
Requires-Python: >=3.8
License-File: LICENSE.md
Requires-Dist: pddlgym>=0.0.7
Dynamic: license-file
